<?xml version="1.0" encoding="utf-8" ?>
<Defs>
	<RR_PawnBadge.BadgeDef>
		<defName>01ang</defname>
		<label>Aspirant</label>
		<description>01</description>
		<icon>PawnBadge/209pxl07</icon>
	</RR_PawnBadge.BadgeDef>
	<RR_PawnBadge.BadgeDef>
		<defName>02ang</defname>
		<label>Sublieutenant</label>
		<description>02</description>
		<icon>PawnBadge/209pxl08</icon>
	</RR_PawnBadge.BadgeDef>
	<RR_PawnBadge.BadgeDef>
		<defName>03ang</defname>
		<label>Lieutenant</label>
		<description>03</description>
		<icon>PawnBadge/209pxl09</icon>
	</RR_PawnBadge.BadgeDef>
	<RR_PawnBadge.BadgeDef>
		<defName>04ang</defname>
		<label>Captain</label>
		<description>04</description>
		<icon>PawnBadge/209pxl10</icon>
	</RR_PawnBadge.BadgeDef>
	<RR_PawnBadge.BadgeDef>
		<defName>05ang</defname>
		<label>Major</label>
		<description>05</description>
		<icon>PawnBadge/209pxl11</icon>
	</RR_PawnBadge.BadgeDef>
	<RR_PawnBadge.BadgeDef>
		<defName>06ang</defname>
		<label>Lieutenant-Colonel</label>
		<description>06</description>
		<icon>PawnBadge/209pxl12</icon>
	</RR_PawnBadge.BadgeDef>
	<RR_PawnBadge.BadgeDef>
		<defName>07ang</defname>
		<label>Colonel</label>
		<description>07</description>
		<icon>PawnBadge/209pxl13</icon>
	</RR_PawnBadge.BadgeDef>
	<RR_PawnBadge.BadgeDef>
		<defName>08ang</defname>
		<label>Brigadier</label>
		<description>08</description>
		<icon>PawnBadge/209pxl14</icon>
	</RR_PawnBadge.BadgeDef>
	<RR_PawnBadge.BadgeDef>
		<defName>09ang</defname>
		<label>Lieutenant-General</label>
		<description>09</description>
		<icon>PawnBadge/209pxl15</icon>
	</RR_PawnBadge.BadgeDef>
	<RR_PawnBadge.BadgeDef>
		<defName>10ang</defname>
		<label>General</label>
		<description>10</description>
		<icon>PawnBadge/209pxl16</icon>
	</RR_PawnBadge.BadgeDef>
	<RR_PawnBadge.BadgeDef>
		<defName>11ang</defname>
		<label>General of the Aviation</label>
		<description>11</description>
		<icon>PawnBadge/209pxl17</icon>
	</RR_PawnBadge.BadgeDef>
</Defs>